LICENSE
MANIFEST.in
README.md
run_tests
setup.py
console/__init__.py
console/admin.py
console/conf.py
console/decorators.py
console/forms.py
console/models.py
console/urls.py
console/utils.py
console/views.py
console/views_metrics.py
console/static/.DS_Store
console/static/console/.DS_Store
console/static/console/bootstrap-3.1.1-dist/css/bootstrap-theme.css
console/static/console/bootstrap-3.1.1-dist/css/bootstrap-theme.css.map
console/static/console/bootstrap-3.1.1-dist/css/bootstrap-theme.min.css
console/static/console/bootstrap-3.1.1-dist/css/bootstrap.css
console/static/console/bootstrap-3.1.1-dist/css/bootstrap.css.map
console/static/console/bootstrap-3.1.1-dist/css/bootstrap.min.css
console/static/console/bootstrap-3.1.1-dist/fonts/glyphicons-halflings-regular.eot
console/static/console/bootstrap-3.1.1-dist/fonts/glyphicons-halflings-regular.svg
console/static/console/bootstrap-3.1.1-dist/fonts/glyphicons-halflings-regular.ttf
console/static/console/bootstrap-3.1.1-dist/fonts/glyphicons-halflings-regular.woff
console/static/console/bootstrap-3.1.1-dist/js/bootstrap.js
console/static/console/bootstrap-3.1.1-dist/js/bootstrap.min.js
console/static/console/css/style.css
console/static/console/js/add_tags.js
console/static/console/js/alarm_filter.js
console/static/console/js/functions.js
console/static/console/js/jquery.cookie.js
console/static/console/js/latest_alarms.js
console/static/console/js/metric_detail.js
console/static/console/js/metrics.js
console/static/console/js/multiple_metrics.js
console/static/console/js/reboot_container.js
console/static/console/js/table.js
console/static/console/rickshaw/rickshaw.min.css
console/static/console/rickshaw/rickshaw.min.js
console/static/console/rickshaw/vendor/d3.v3.js
console/static/console/tablesorter/.DS_Store
console/static/console/tablesorter/css/.DS_Store
console/static/console/tablesorter/css/theme.bootstrap.css
console/static/console/tablesorter/css/images/black-asc.gif
uwsgiit_console.egg-info/PKG-INFO
uwsgiit_console.egg-info/SOURCES.txt
uwsgiit_console.egg-info/dependency_links.txt
uwsgiit_console.egg-info/requires.txt
uwsgiit_console.egg-info/top_level.txt