Metadata-Version: 1.1
Name: uwsgiit-console
Version: 0.3.3
Summary: A django app to simplify the use of uWSGI.it API
Home-page: https://github.com/20tab/uwsgiit_console
Author: 20tab S.r.l.
Author-email: info@20tab.com
License: MIT License
Keywords: uwsgit.it,console
Platform: OS Independent
Classifier: Development Status :: 4 - Beta
Classifier: Environment :: Web Environment
Classifier: Framework :: Django
Classifier: Operating System :: OS Independent
Classifier: Programming Language :: Python :: 2.7
Classifier: Programming Language :: Python :: 3
Classifier: Programming Language :: JavaScript
Classifier: Topic :: Internet :: WWW/HTTP
Classifier: Topic :: Internet :: WWW/HTTP :: Dynamic Content
Classifier: Topic :: Software Development :: Libraries :: Python Modules
